diapyr/__init__.py
diapyr/ctor.py
diapyr/diapyr.py
diapyr/iface.py
diapyr/match.py
diapyr/source.py
diapyr/start.py
diapyr/util.py
setuphacks/__init__.py
setuphacks/ez_setup.py
setuphacks/fakesetup.py
setuphacks/Cython/Build.py
setuphacks/Cython/__init__.py
diapyr-38.dist-info/METADATA
diapyr-38.dist-info/WHEEL
diapyr-38.dist-info/top_level.txt
diapyr-38.dist-info/RECORD
