Metadata-Version: 2.1
Name: diapyr
Version: 38
Summary: Constructor injection for Python
Home-page: https://pypi.org/project/diapyr/
Author: foyono
Author-email: shrovis@foyono.com
Requires-Dist: foyndation>=12
